{
  "project_info": {
    "project_number": "1088092766920",
    "firebase_url": "https://spacetrader-f001a.firebaseio.com",
    "project_id": "spacetrader-f001a",
    "storage_bucket": "spacetrader-f001a.appspot.com"
  },
  "client": [
    {
      "client_info": {
        "mobilesdk_app_id": "1:1088092766920:android:7364e0a235c59e5e",
        "android_client_info": {
          "package_name": "edu.gatech.cs2340.team49x.spacetrader"
        }
      },
      "oauth_client": [
        {
          "client_id": "1088092766920-20irkads7kfcjqlok1the5efk4815rrv.apps.googleusercontent.com",
          "client_type": 3
        }
      ],
      "api_key": [
        {
          "current_key": "AIzaSyCs3FQsDUi621zDWbnEHBWKsbOhDzrnCxc"
        }
      ],
      "services": {
        "appinvite_service": {
          "other_platform_oauth_client": [
            {
              "client_id": "1088092766920-20irkads7kfcjqlok1the5efk4815rrv.apps.googleusercontent.com",
              "client_type": 3
            }
          ]
        }
      }
    }
  ],
  "configuration_version": "1"
}